{
    "generation": {
        "cave_id": 1,
        "length": 20.0,
        "radius": 2.0,
        "num_segments": 10,
        "points_per_circle": 12,
        "offset_magnitude": 2,
        "num_dents": 3,
        "curve_intensity": 0.3171128260027241
    },
    "original_mesh": {
        "vertex_count": 120,
        "face_count": 216,
        "is_watertight": false
    },
    "voxelization": {
        "voxel_size": 0.1,
        "voxel_count": 32891
    },
    "target_pos": {
        "x": 20.0,
        "y": 3.2,
        "z": 1.0
    },
    "voxel_mesh": {
        "vertex_count": 68622,
        "face_count": 394692
    },
    "mujoco_boxes": {
        "original_box_count": 32891,
        "merged_box_count": 4113
    }
}